homework1_package_Olesja_Tsimmerman/First homework.py
homework1_package_Olesja_Tsimmerman/__init__.py
homework1_package_Olesja_Tsimmerman-0.0.1.dist-info/LICENSE
homework1_package_Olesja_Tsimmerman-0.0.1.dist-info/METADATA
homework1_package_Olesja_Tsimmerman-0.0.1.dist-info/WHEEL
homework1_package_Olesja_Tsimmerman-0.0.1.dist-info/top_level.txt
homework1_package_Olesja_Tsimmerman-0.0.1.dist-info/RECORD
